bits/__init__.py
bits/bitsdb/__init__.py
bits/bitsdb/bitsdbapi.py
bits/bitsdb/cloudfunctions.py
bits/bitsdb/datastore.py
bits/bitsdb/firestore.py
bits/bitsdb/mongodb.py
bits/bitsdb/update.py
bits_bitsdb-2.0.0.dist-info/METADATA
bits_bitsdb-2.0.0.dist-info/WHEEL
bits_bitsdb-2.0.0.dist-info/RECORD
