Metadata-Version: 2.4
Name: bits-bitsdb
Version: 2.0.0
Summary: BITS BITSdb
License-Expression: BSD-3-Clause
Keywords: bits,bitsdb
Author: Dev Null
Author-email: <devnull@broadinstitute.org>
Requires-Python: >=3.9
Classifier: Programming Language :: Python :: 3
Classifier: Programming Language :: Python :: 3.9
Classifier: Programming Language :: Python :: 3.10
Classifier: Programming Language :: Python :: 3.11
Classifier: Programming Language :: Python :: 3.12
Classifier: Programming Language :: Python :: 3.13
Classifier: Programming Language :: Python :: 3.14
Requires-Dist: bits-google (>=2.0.0,<3.0.0)
Requires-Dist: bits-mongo (>=1.0.4,<2.0.0)
Project-URL: Homepage, https://github.com/broadinstitute/bits-bitsdb.git
Project-URL: Repository, https://github.com/broadinstitute/bits-bitsdb.git
